[{"kind": "customsearch#result", "title": "Wood Grain/Texture | The Wood Database", "displayLink": "www.wood-database.com", "htmlTitle": "Wood Grain/<b>Texture</b> | The Wood Database", "snippet": "narra-ribbon-stripe", "htmlSnippet": "narra-ribbon-stripe", "link": "http://www.wood-database.com/wp-content/uploads/narra-ribbon-stripe.jpg", "mime": "image/jpeg", "image": {"thumbnailWidth": 135, "byteSize": 281071, "height": 600, "width": 600, "contextLink": "http://www.wood-database.com/wood-articles/wood-grain-texture/", "thumbnailLink": "https://encrypted-tbn1.gstatic.com/images?q=tbn:ANd9GcSMS2H6qJUeDxiRzDBsv4cnHiRM8OToMGuG__8pnAFXNIsqePFTK8-ZRCP0EA", "thumbnailHeight": 135}}, {"kind": "customsearch#result", "title": "Bronzed Weng\u00e9 | Premium Wood Prints | Lamin-Art", "displayLink": "www.laminart.com", "htmlTitle": "Bronzed Weng\u00e9 | Premium Wood Prints | Lamin-Art", "snippet": "2610 Bronzed Weng\u00e9 - Textured", "htmlSnippet": "2610 Bronzed Weng\u00e9 - <b>Textured</b>", "link": "http://www.laminart.com/img/product/cad/26_2610_cad.jpg", "mime": "image/jpeg", "image": {"thumbnailWidth": 150, "byteSize": 1004262, "height": 1400, "width": 1400, "contextLink": "http://www.laminart.com/products-samples/decorative-laminate/premium-wood-prints/54/bronzed-wenge", "thumbnailLink": "https://encrypted-tbn1.gstatic.com/images?q=tbn:ANd9GcTdICJQJZGhg7LZKust_EZTDCwEJt3Iu1Toy6_uHsMMyKGArxMc95LbN6AQxA", "thumbnailHeight": 150}}, {"kind": "customsearch#result", "title": "Fancy Walnut | Premium Wood Prints | Lamin-Art", "displayLink": "www.laminart.com", "htmlTitle": "Fancy Walnut | Premium Wood Prints | Lamin-Art", "snippet": "2608 Fancy Walnut - Textured", "htmlSnippet": "2608 Fancy Walnut - <b>Textured</b>", "link": "http://www.laminart.com/img/product/cad/25_2608_cad.jpg", "mime": "image/jpeg", "image": {"thumbnailWidth": 150, "byteSize": 951608, "height": 1400, "width": 1400, "contextLink": "http://www.laminart.com/products-samples/decorative-laminate/premium-wood-prints/52/fancy-walnut", "thumbnailLink": "https://encrypted-tbn0.gstatic.com/images?q=tbn:ANd9GcRo4BadNJbYFsMM6IbsOZNfPrwVlO_5a63tumaTszlDeUoemqNc5ozHsbAk", "thumbnailHeight": 150}}, {"kind": "customsearch#result", "title": "Bamboo | The Wood Database - Lumber Identification (Monocots)", "displayLink": "www.wood-database.com", "htmlTitle": "Bamboo | The Wood Database - Lumber Identification (Monocots)", "snippet": "Bamboo: horizontal (sanded)", "htmlSnippet": "Bamboo: horizontal (sanded)", "link": "http://www.wood-database.com/wp-content/uploads/bamboo-fs.jpg", "mime": "image/jpeg", "image": {"thumbnailWidth": 135, "byteSize": 89893, "height": 600, "width": 600, "contextLink": "http://www.wood-database.com/lumber-identification/monocots/bamboo/", "thumbnailLink": "https://encrypted-tbn3.gstatic.com/images?q=tbn:ANd9GcS1k9DPsPV5VudwHxQfBb-LL_ESB0bWkSBBVIrKN7YBROPWzaSZLCkd0Ic4", "thumbnailHeight": 135}}, {"kind": "customsearch#result", "title": "Natural Coco | Discontinued | Lamin-Art", "displayLink": "www.laminart.com", "htmlTitle": "Natural Coco | Discontinued | Lamin-Art", "snippet": "3104 Natural Coco - Textured", "htmlSnippet": "3104 Natural Coco - <b>Textured</b>", "link": "http://www.laminart.com/img/product/cad/60_3104_cad.jpg", "mime": "image/jpeg", "image": {"thumbnailWidth": 150, "byteSize": 1132141, "height": 1400, "width": 1400, "contextLink": "http://www.laminart.com/products-samples/discontinued/79/natural-coco", "thumbnailLink": "https://encrypted-tbn0.gstatic.com/images?q=tbn:ANd9GcRMp3f5bxqQVQVWZjNTqCBiEftB-cVbatZDbdC6mfshSc8EsJdFIY5u39jd2Q", "thumbnailHeight": 150}}, {"kind": "customsearch#result", "title": "Golden Satinwood | Premium Wood Prints | Lamin-Art", "displayLink": "www.laminart.com", "htmlTitle": "Golden Satinwood | Premium Wood Prints | Lamin-Art", "snippet": "Satinwood - Textured (T)", "htmlSnippet": "Satinwood - <b>Textured</b> (T)", "link": "http://www.laminart.com/img/product/cad/41_3020_cad.jpg", "mime": "image/jpeg", "image": {"thumbnailWidth": 150, "byteSize": 590796, "height": 1400, "width": 1400, "contextLink": "http://www.laminart.com/products-samples/decorative-laminate/premium-wood-prints/63/golden-satinwood", "thumbnailLink": "https://encrypted-tbn2.gstatic.com/images?q=tbn:ANd9GcThd0OKfHX3bL18ULptW-FKCrpH766cjvmnB9zzamUSaNTsYXAgDeq19F9m", "thumbnailHeight": 150}}, {"kind": "customsearch#result", "title": "Sorting Out Satinwoods | The Wood Database", "displayLink": "www.wood-database.com", "htmlTitle": "Sorting Out Satinwoods | The Wood Database", "snippet": "Satinwood (fine texture)", "htmlSnippet": "Satinwood (fine <b>texture</b>)", "link": "http://www.wood-database.com/wp-content/uploads/west-indian-satinwood-texture.jpg", "mime": "image/jpeg", "image": {"thumbnailWidth": 104, "byteSize": 27762, "height": 200, "width": 200, "contextLink": "http://www.wood-database.com/wood-articles/sorting-out-satinwoods/", "thumbnailLink": "https://encrypted-tbn1.gstatic.com/images?q=tbn:ANd9GcSNtIDujz9hxte4lU4oirxfaIgXjKrRzK-zqBTwwott23hP4awcUQPCpg", "thumbnailHeight": 104}}, {"kind": "customsearch#result", "title": "The Source | Lamin-Art", "displayLink": "www.laminart.com", "htmlTitle": "The Source | Lamin-Art", "snippet": "in Color and Texture", "htmlSnippet": "in Color and <b>Texture</b>", "link": "http://www.laminart.com/newsletter/img/products/61_976_Tropical.jpg", "mime": "image/jpeg", "image": {"thumbnailWidth": 106, "byteSize": 13587, "height": 213, "width": 214, "contextLink": "http://www.laminart.com/new/newsletter/61/real-wood-only-better", "thumbnailLink": "https://encrypted-tbn1.gstatic.com/images?q=tbn:ANd9GcSQizDpVVQlh5vtDjrh8qY-xniIMQGP9V-H2ZiWOYdigpNhfDMRocjhnQ", "thumbnailHeight": 106}}, {"kind": "customsearch#result", "title": "Guanacaste | The Wood Database - Lumber Identification (Hardwoods)", "displayLink": "www.wood-database.com", "htmlTitle": "Guanacaste | The Wood Database - Lumber Identification (Hardwoods)", "snippet": "Guanacaste (sealed)", "htmlSnippet": "Guanacaste (sealed)", "link": "http://www.wood-database.com/wp-content/uploads/guanacaste-sealed.jpg", "mime": "image/jpeg", "image": {"thumbnailWidth": 99, "byteSize": 184119, "height": 600, "width": 440, "contextLink": "http://www.wood-database.com/lumber-identification/hardwoods/guanacaste/", "thumbnailLink": "https://encrypted-tbn0.gstatic.com/images?q=tbn:ANd9GcSNI4bCr127tm37q02xD_WQ2UTvaWpEyvnFPeXSS2TQJRvOlx4mo8S4IiU", "thumbnailHeight": 135}}, {"kind": "customsearch#result", "title": "Paper Birch | The Wood Database - Lumber Identification (Hardwoods)", "displayLink": "www.wood-database.com", "htmlTitle": "Paper Birch | The Wood Database - Lumber Identification (Hardwoods)", "snippet": "paper-birch.jpg", "htmlSnippet": "paper-birch.jpg", "link": "http://www.wood-database.com/wp-content/uploads/paper-birch.jpg", "mime": "image/jpeg", "image": {"thumbnailWidth": 100, "byteSize": 150764, "height": 600, "width": 445, "contextLink": "http://www.wood-database.com/lumber-identification/hardwoods/paper-birch/", "thumbnailLink": "https://encrypted-tbn3.gstatic.com/images?q=tbn:ANd9GcRv66UuVhlgnmfMyu6y0W90FoQeWuJs5OTp7npCNGn_33v9_KNlZ2PxAbjf", "thumbnailHeight": 135}}, {"kind": "customsearch#result", "title": "Wood Grain/Texture | The Wood Database", "displayLink": "www.wood-database.com", "htmlTitle": "Wood Grain/<b>Texture</b> | The Wood Database", "snippet": "Black Walnut (crotch)", "htmlSnippet": "Black Walnut (crotch)", "link": "http://www.wood-database.com/wp-content/uploads/black-walnut-crotch-s.jpg", "mime": "image/jpeg", "image": {"thumbnailWidth": 90, "byteSize": 62511, "height": 600, "width": 400, "contextLink": "http://www.wood-database.com/wood-articles/wood-grain-texture/", "thumbnailLink": "https://encrypted-tbn0.gstatic.com/images?q=tbn:ANd9GcR5IPkGP3-TECzjBpi1b2xN0ckEPGLxC1WUu7LWJY_HInWH3s1s-swvVVM", "thumbnailHeight": 135}}, {"kind": "customsearch#result", "title": "Natural Ash | Premium Wood Prints | Lamin-Art", "displayLink": "www.laminart.com", "htmlTitle": "Natural Ash | Premium Wood Prints | Lamin-Art", "snippet": "3054 Natural Ash - Fine Grain", "htmlSnippet": "3054 Natural Ash - Fine Grain", "link": "http://www.laminart.com/img/product/cad/896_3054.jpg", "mime": "image/jpeg", "image": {"thumbnailWidth": 150, "byteSize": 1237011, "height": 1400, "width": 1400, "contextLink": "http://www.laminart.com/products-samples/decorative-laminate/premium-wood-prints/521/natural-ash", "thumbnailLink": "https://encrypted-tbn0.gstatic.com/images?q=tbn:ANd9GcSkn6xEVRdr_LvdYL2jc189uXGqSFzcGkZPEqgPMrNNKOqBxlX6vJvOl7ppKQ", "thumbnailHeight": 150}}, {"kind": "customsearch#result", "title": "Guanacaste | The Wood Database - Lumber Identification (Hardwoods)", "displayLink": "www.wood-database.com", "htmlTitle": "Guanacaste | The Wood Database - Lumber Identification (Hardwoods)", "snippet": "Guanacaste (Enterolobium", "htmlSnippet": "Guanacaste (Enterolobium", "link": "http://www.wood-database.com/wp-content/uploads/guanacaste.jpg", "mime": "image/jpeg", "image": {"thumbnailWidth": 99, "byteSize": 173036, "height": 600, "width": 440, "contextLink": "http://www.wood-database.com/lumber-identification/hardwoods/guanacaste/", "thumbnailLink": "https://encrypted-tbn1.gstatic.com/images?q=tbn:ANd9GcT1vbHrjGDL2Kd9CZDxAtk_5obllGen-I-MOPN5QuGarspt_YhNLh91ykI", "thumbnailHeight": 135}}, {"kind": "customsearch#result", "title": "Balsa | The Wood Database - Lumber Identification (Hardwoods)", "displayLink": "www.wood-database.com", "htmlTitle": "Balsa | The Wood Database - Lumber Identification (Hardwoods)", "snippet": "Balsa (Ochroma pyramidale)", "htmlSnippet": "Balsa (Ochroma pyramidale)", "link": "http://www.wood-database.com/wp-content/uploads/balsa-s.jpg", "mime": "image/jpeg", "image": {"thumbnailWidth": 135, "byteSize": 98439, "height": 600, "width": 600, "contextLink": "http://www.wood-database.com/lumber-identification/hardwoods/balsa/", "thumbnailLink": "https://encrypted-tbn0.gstatic.com/images?q=tbn:ANd9GcTLVHAbdS8GTMJtvuIKqgMa1MgMuXrgrN-AYvhCfCyvY-0I9vCCKXCOArKN", "thumbnailHeight": 135}}, {"kind": "customsearch#result", "title": "Okoume | The Wood Database - Lumber Identification (Hardwoods)", "displayLink": "www.wood-database.com", "htmlTitle": "Okoume | The Wood Database - Lumber Identification (Hardwoods)", "snippet": "Okoume (sealed)", "htmlSnippet": "Okoume (sealed)", "link": "http://www.wood-database.com/wp-content/uploads/okoume-sealed-s.jpg", "mime": "image/jpeg", "image": {"thumbnailWidth": 135, "byteSize": 162331, "height": 600, "width": 600, "contextLink": "http://www.wood-database.com/lumber-identification/hardwoods/okoume/", "thumbnailLink": "https://encrypted-tbn0.gstatic.com/images?q=tbn:ANd9GcRTZK9pKuLrt3VDkxQcC1wjaTONeixXWPsGfHFGYQlqKMxSxqwSGhMByIke", "thumbnailHeight": 135}}, {"kind": "customsearch#result", "title": "Engelmann Spruce | The Wood Database - Lumber Identification ...", "displayLink": "www.wood-database.com", "htmlTitle": "Engelmann Spruce | The Wood Database - Lumber Identification <b>...</b>", "snippet": "Engelmann Spruce (sealed)", "htmlSnippet": "Engelmann Spruce (sealed)", "link": "http://www.wood-database.com/wp-content/uploads/engelmann-spruce-sealed.jpg", "mime": "image/jpeg", "image": {"thumbnailWidth": 99, "byteSize": 121726, "height": 600, "width": 440, "contextLink": "http://www.wood-database.com/lumber-identification/softwoods/engelmann-spruce/", "thumbnailLink": "https://encrypted-tbn2.gstatic.com/images?q=tbn:ANd9GcSukW82CTkDwBNanFjCxR-NfLehmNuJQyiUw75uADoHsubwGiw13V5Fo9JU", "thumbnailHeight": 135}}, {"kind": "customsearch#result", "title": "Red Palm | The Wood Database - Lumber Identification (Monocots)", "displayLink": "www.wood-database.com", "htmlTitle": "Red Palm | The Wood Database - Lumber Identification (Monocots)", "snippet": "Red Palm (sealed)", "htmlSnippet": "Red Palm (sealed)", "link": "http://www.wood-database.com/wp-content/uploads/red-palm-sealed.jpg", "mime": "image/jpeg", "image": {"thumbnailWidth": 135, "byteSize": 163236, "height": 600, "width": 600, "contextLink": "http://www.wood-database.com/lumber-identification/monocots/red-palm/", "thumbnailLink": "https://encrypted-tbn3.gstatic.com/images?q=tbn:ANd9GcQ6yMTTEFQXZR4cyKfSrAXeysS28F_kWUKbl9_9ndwZpd4xFAWkUYHnt0Rr1A", "thumbnailHeight": 135}}, {"kind": "customsearch#result", "title": "East Indian Rosewood | The Wood Database - Lumber Identification ...", "displayLink": "www.wood-database.com", "htmlTitle": "East Indian Rosewood | The Wood Database - Lumber Identification <b>...</b>", "snippet": "East Indian Rosewood (sealed)", "htmlSnippet": "East Indian Rosewood (sealed)", "link": "http://www.wood-database.com/wp-content/uploads/east-indian-rosewood-sealed.jpg", "mime": "image/jpeg", "image": {"thumbnailWidth": 135, "byteSize": 76351, "height": 600, "width": 600, "contextLink": "http://www.wood-database.com/lumber-identification/hardwoods/east-indian-rosewood/", "thumbnailLink": "https://encrypted-tbn2.gstatic.com/images?q=tbn:ANd9GcSBDmpvtUVHFeYfSxsMcl2IDnGd79mlSq_rw9YmP_CtPLifA-s8YVgNE1mH", "thumbnailHeight": 135}}, {"kind": "customsearch#result", "title": "Hard Maple | The Wood Database - Lumber Identification (Hardwoods)", "displayLink": "www.wood-database.com", "htmlTitle": "Hard Maple | The Wood Database - Lumber Identification (Hardwoods)", "snippet": "Hard Maple (burl)", "htmlSnippet": "Hard Maple (burl)", "link": "http://www.wood-database.com/wp-content/uploads/hard-maple-burl-s.jpg", "mime": "image/jpeg", "image": {"thumbnailWidth": 135, "byteSize": 114814, "height": 600, "width": 600, "contextLink": "http://www.wood-database.com/lumber-identification/hardwoods/hard-maple/", "thumbnailLink": "https://encrypted-tbn1.gstatic.com/images?q=tbn:ANd9GcTHtaZ--1Qcst0xwjXO36-xnv9wXK1F8fgx47dCzc45424yNrrQV5tDk1d1Qw", "thumbnailHeight": 135}}, {"kind": "customsearch#result", "title": "Balsa | The Wood Database - Lumber Identification (Hardwoods)", "displayLink": "www.wood-database.com", "htmlTitle": "Balsa | The Wood Database - Lumber Identification (Hardwoods)", "snippet": "Balsa (sealed)", "htmlSnippet": "Balsa (sealed)", "link": "http://www.wood-database.com/wp-content/uploads/balsa-sealed-s.jpg", "mime": "image/jpeg", "image": {"thumbnailWidth": 135, "byteSize": 125029, "height": 600, "width": 600, "contextLink": "http://www.wood-database.com/lumber-identification/hardwoods/balsa/", "thumbnailLink": "https://encrypted-tbn0.gstatic.com/images?q=tbn:ANd9GcRg4zOquSJZANTzOO7sjVvEJ-X3J7g6cbgJTiqLO8xrsi8GY2GnlXetuaSd", "thumbnailHeight": 135}}, {"kind": "customsearch#result", "title": "Laquered Coco | Premium Wood Prints | Lamin-Art", "displayLink": "www.laminart.com", "htmlTitle": "Laquered Coco | Premium Wood Prints | Lamin-Art", "snippet": "3103 Laquered Coco - Textured", "htmlSnippet": "3103 Laquered Coco - <b>Textured</b>", "link": "http://www.laminart.com/img/product/cad/58_3103_cad.jpg", "mime": "image/jpeg", "image": {"thumbnailWidth": 150, "byteSize": 2539262, "height": 1400, "width": 1400, "contextLink": "http://www.laminart.com/products-samples/decorative-laminate/premium-wood-prints/77/laquered-coco", "thumbnailLink": "https://encrypted-tbn2.gstatic.com/images?q=tbn:ANd9GcRZIWbSFQDqvH4DQhDDtjc85voka_3jjPY-rn0lcWYj21Tx7JNOJ5QBVKKm", "thumbnailHeight": 150}}, {"kind": "customsearch#result", "title": "Narra | The Wood Database - Lumber Identification (Hardwoods)", "displayLink": "www.wood-database.com", "htmlTitle": "Narra | The Wood Database - Lumber Identification (Hardwoods)", "snippet": "Narra (sealed)", "htmlSnippet": "Narra (sealed)", "link": "http://www.wood-database.com/wp-content/uploads/narra-sealed-3.jpg", "mime": "image/jpeg", "image": {"thumbnailWidth": 135, "byteSize": 128169, "height": 600, "width": 600, "contextLink": "http://www.wood-database.com/lumber-identification/hardwoods/narra/", "thumbnailLink": "https://encrypted-tbn1.gstatic.com/images?q=tbn:ANd9GcQ4-L8HCk3sojgjlQj6bywHfqzIsVvMam93u0Bj_7wM2wodDBkudzoCOdGTYg", "thumbnailHeight": 135}}, {"kind": "customsearch#result", "title": "Norway Spruce | The Wood Database - Lumber Identification (Softwoods)", "displayLink": "www.wood-database.com", "htmlTitle": "Norway Spruce | The Wood Database - Lumber Identification (Softwoods)", "snippet": "Norway Spruce (sealed)", "htmlSnippet": "Norway Spruce (sealed)", "link": "http://www.wood-database.com/wp-content/uploads/norway-spruce-sealed.jpg", "mime": "image/jpeg", "image": {"thumbnailWidth": 98, "byteSize": 146640, "height": 600, "width": 435, "contextLink": "http://www.wood-database.com/lumber-identification/softwoods/norway-spruce/", "thumbnailLink": "https://encrypted-tbn3.gstatic.com/images?q=tbn:ANd9GcTvS7sbju-veXDY_plZU4biX7cSRGGXEHPm-GpG399rrioWapfCC1Xfd7Vr", "thumbnailHeight": 135}}, {"kind": "customsearch#result", "title": "Red Palm | The Wood Database - Lumber Identification (Monocots)", "displayLink": "www.wood-database.com", "htmlTitle": "Red Palm | The Wood Database - Lumber Identification (Monocots)", "snippet": "Red Palm (Cocos nucifera)", "htmlSnippet": "Red Palm (Cocos nucifera)", "link": "http://www.wood-database.com/wp-content/uploads/red-palm.jpg", "mime": "image/jpeg", "image": {"thumbnailWidth": 135, "byteSize": 175031, "height": 600, "width": 600, "contextLink": "http://www.wood-database.com/lumber-identification/monocots/red-palm/", "thumbnailLink": "https://encrypted-tbn2.gstatic.com/images?q=tbn:ANd9GcQarRsYErDAzgO0agPHMaqkTyqB2eG1FUEZKQxhs1mewMJkpBKjBVqgJBF9", "thumbnailHeight": 135}}, {"kind": "customsearch#result", "title": "Bamboo | The Wood Database - Lumber Identification (Monocots)", "displayLink": "www.wood-database.com", "htmlTitle": "Bamboo | The Wood Database - Lumber Identification (Monocots)", "snippet": "Bamboo: vertical (sealed)", "htmlSnippet": "Bamboo: vertical (sealed)", "link": "http://www.wood-database.com/wp-content/uploads/bamboo-qs-sealed.jpg", "mime": "image/jpeg", "image": {"thumbnailWidth": 135, "byteSize": 89178, "height": 600, "width": 600, "contextLink": "http://www.wood-database.com/lumber-identification/monocots/bamboo/", "thumbnailLink": "https://encrypted-tbn3.gstatic.com/images?q=tbn:ANd9GcSIVKuaxI-ZIvOjsGhxO0_rh9Nv7zC21R3oJ_t4078s-XIkOuZjQsI_6Yfd", "thumbnailHeight": 135}}, {"kind": "customsearch#result", "title": "Teak | The Wood Database - Lumber Identification (Hardwoods)", "displayLink": "www.wood-database.com", "htmlTitle": "Teak | The Wood Database - Lumber Identification (Hardwoods)", "snippet": "Teak (sealed)", "htmlSnippet": "Teak (sealed)", "link": "http://www.wood-database.com/wp-content/uploads/teak-sealed1.jpg", "mime": "image/jpeg", "image": {"thumbnailWidth": 135, "byteSize": 110910, "height": 600, "width": 600, "contextLink": "http://www.wood-database.com/lumber-identification/hardwoods/teak/", "thumbnailLink": "https://encrypted-tbn3.gstatic.com/images?q=tbn:ANd9GcR3DY8DlIoK1cMsGiCxezJ6EngAHsEDWVh73DfIG5Kx6kXbIP31dbc0iJcAKA", "thumbnailHeight": 135}}, {"kind": "customsearch#result", "title": "Virginia Pine | The Wood Database - Lumber Identification (Softwoods)", "displayLink": "www.wood-database.com", "htmlTitle": "Virginia Pine | The Wood Database - Lumber Identification (Softwoods)", "snippet": "Virginia Pine (Pinus", "htmlSnippet": "Virginia Pine (Pinus", "link": "http://www.wood-database.com/wp-content/uploads/virginia-pine.jpg", "mime": "image/jpeg", "image": {"thumbnailWidth": 104, "byteSize": 132344, "height": 600, "width": 460, "contextLink": "http://www.wood-database.com/lumber-identification/softwoods/virginia-pine/", "thumbnailLink": "https://encrypted-tbn0.gstatic.com/images?q=tbn:ANd9GcQIXn_geU0YRWyqsQYvuDRVrelvN-nZM6np5FLFylg6PinBRzpPh4q-pa7u", "thumbnailHeight": 135}}, {"kind": "customsearch#result", "title": "Eastern White Pine | The Wood Database - Lumber Identification ...", "displayLink": "www.wood-database.com", "htmlTitle": "Eastern White Pine | The Wood Database - Lumber Identification <b>...</b>", "snippet": "Eastern White Pine (Pinus", "htmlSnippet": "Eastern White Pine (Pinus", "link": "http://www.wood-database.com/wp-content/uploads/eastern-white-pine.jpg", "mime": "image/jpeg", "image": {"thumbnailWidth": 101, "byteSize": 78645, "height": 600, "width": 450, "contextLink": "http://www.wood-database.com/lumber-identification/softwoods/eastern-white-pine/", "thumbnailLink": "https://encrypted-tbn3.gstatic.com/images?q=tbn:ANd9GcR8iaVYG54WZeimxJ8twqqTBdz6_GCWQI9oCyX-FhqhA4OtZFLoI9xaBBs", "thumbnailHeight": 135}}, {"kind": "customsearch#result", "title": "Mango | The Wood Database - Lumber Identification (Hardwoods)", "displayLink": "www.wood-database.com", "htmlTitle": "Mango | The Wood Database - Lumber Identification (Hardwoods)", "snippet": "Mango (Mangifera indica)", "htmlSnippet": "Mango (Mangifera indica)", "link": "http://www.wood-database.com/wp-content/uploads/mango.jpg", "mime": "image/jpeg", "image": {"thumbnailWidth": 135, "byteSize": 325675, "height": 600, "width": 600, "contextLink": "http://www.wood-database.com/lumber-identification/hardwoods/mango/", "thumbnailLink": "https://encrypted-tbn0.gstatic.com/images?q=tbn:ANd9GcTs_tByoSTz28ZUvkkBJWAvMs9uugbUW42TgytJfIX1X1PPIyt5qmjdrJHqaA", "thumbnailHeight": 135}}, {"kind": "customsearch#result", "title": "Western Red Cedar | The Wood Database - Lumber Identification ...", "displayLink": "www.wood-database.com", "htmlTitle": "Western Red Cedar | The Wood Database - Lumber Identification <b>...</b>", "snippet": "Western Red Cedar (sealed)", "htmlSnippet": "Western Red Cedar (sealed)", "link": "http://www.wood-database.com/wp-content/uploads/western-red-cedar-sealed.jpg", "mime": "image/jpeg", "image": {"thumbnailWidth": 135, "byteSize": 99643, "height": 600, "width": 600, "contextLink": "http://www.wood-database.com/lumber-identification/softwoods/western-red-cedar/", "thumbnailLink": "https://encrypted-tbn1.gstatic.com/images?q=tbn:ANd9GcQr_Wk9N4Rk19Jgsck9Qv_syU9KZQyD45yF3Cik1U0Y6e5NsYwNhX6OHESRoQ", "thumbnailHeight": 135}}, {"kind": "customsearch#result", "title": "Sycamore Maple | The Wood Database - Lumber Identification (Hardwoods)", "displayLink": "www.wood-database.com", "htmlTitle": "Sycamore Maple | The Wood Database - Lumber Identification (Hardwoods)", "snippet": "Sycamore Maple (sealed)", "htmlSnippet": "Sycamore Maple (sealed)", "link": "http://www.wood-database.com/wp-content/uploads/sycamore-maple-sealed-s.jpg", "mime": "image/jpeg", "image": {"thumbnailWidth": 135, "byteSize": 114631, "height": 600, "width": 600, "contextLink": "http://www.wood-database.com/lumber-identification/hardwoods/sycamore-maple/", "thumbnailLink": "https://encrypted-tbn0.gstatic.com/images?q=tbn:ANd9GcRohM2CIH5ySLvr67_WW1QVl6w4BE_BwAWtin_4T-Y-5ZSs_TQy2-RQjncj", "thumbnailHeight": 135}}, {"kind": "customsearch#result", "title": "Red Oak | The Wood Database - Lumber Identification (Hardwoods)", "displayLink": "www.wood-database.com", "htmlTitle": "Red Oak | The Wood Database - Lumber Identification (Hardwoods)", "snippet": "Red Oak (sealed)", "htmlSnippet": "Red Oak (sealed)", "link": "http://www.wood-database.com/wp-content/uploads/red-oak-sealed.jpg", "mime": "image/jpeg", "image": {"thumbnailWidth": 135, "byteSize": 99229, "height": 600, "width": 600, "contextLink": "http://www.wood-database.com/lumber-identification/hardwoods/red-oak/", "thumbnailLink": "https://encrypted-tbn2.gstatic.com/images?q=tbn:ANd9GcSHVx6IJAT-t803VRF6LyoA_aEGebIPk9HOWST-LiJvDMB1SXJVdk2201WF", "thumbnailHeight": 135}}, {"kind": "customsearch#result", "title": "Red Spruce | The Wood Database - Lumber Identification (Softwoods)", "displayLink": "www.wood-database.com", "htmlTitle": "Red Spruce | The Wood Database - Lumber Identification (Softwoods)", "snippet": "Red Spruce (Picea rubens)", "htmlSnippet": "Red Spruce (Picea rubens)", "link": "http://www.wood-database.com/wp-content/uploads/red-spruce.jpg", "mime": "image/jpeg", "image": {"thumbnailWidth": 99, "byteSize": 146095, "height": 600, "width": 440, "contextLink": "http://www.wood-database.com/lumber-identification/softwoods/red-spruce/", "thumbnailLink": "https://encrypted-tbn1.gstatic.com/images?q=tbn:ANd9GcTH3TuLKl2Z7cxIEJKW85ZL1Zw7D8h9rGoU8G4wLosQtY5mhfQzJYMWEeE", "thumbnailHeight": 135}}, {"kind": "customsearch#result", "title": "Spruce Pine | The Wood Database - Lumber Identification (Softwoods)", "displayLink": "www.wood-database.com", "htmlTitle": "Spruce Pine | The Wood Database - Lumber Identification (Softwoods)", "snippet": "Sand Pine (Pinus clausa)", "htmlSnippet": "Sand Pine (Pinus clausa)", "link": "http://www.wood-database.com/wp-content/uploads/sand-pine.jpg", "mime": "image/jpeg", "image": {"thumbnailWidth": 101, "byteSize": 127318, "height": 600, "width": 450, "contextLink": "http://www.wood-database.com/lumber-identification/softwoods/spruce-pine/", "thumbnailLink": "https://encrypted-tbn3.gstatic.com/images?q=tbn:ANd9GcRA0jCKOrIGi-q2IR0GnJBFBnpxXGL_SaSr29nVIVK48CgcmHq-k7FyoF88", "thumbnailHeight": 135}}, {"kind": "customsearch#result", "title": "Spanish Cedar | The Wood Database - Lumber Identification (Hardwoods)", "displayLink": "www.wood-database.com", "htmlTitle": "Spanish Cedar | The Wood Database - Lumber Identification (Hardwoods)", "snippet": "spanish-cedar.jpg", "htmlSnippet": "spanish-cedar.jpg", "link": "http://www.wood-database.com/wp-content/uploads/spanish-cedar.jpg", "mime": "image/jpeg", "image": {"thumbnailWidth": 135, "byteSize": 102523, "height": 600, "width": 600, "contextLink": "http://www.wood-database.com/lumber-identification/hardwoods/spanish-cedar/", "thumbnailLink": "https://encrypted-tbn2.gstatic.com/images?q=tbn:ANd9GcROJ8UtY5IxODDgWHsUr5ESnenn1Pu1DbMBvVYdV9hv7jVDvHFyWbZGJ5uP", "thumbnailHeight": 135}}, {"kind": "customsearch#result", "title": "Koa | The Wood Database - Lumber Identification (Hardwoods)", "displayLink": "www.wood-database.com", "htmlTitle": "Koa | The Wood Database - Lumber Identification (Hardwoods)", "snippet": "Koa (Acacia koa)", "htmlSnippet": "Koa (Acacia koa)", "link": "http://www.wood-database.com/wp-content/uploads/koa.jpg", "mime": "image/jpeg", "image": {"thumbnailWidth": 135, "byteSize": 152670, "height": 600, "width": 600, "contextLink": "http://www.wood-database.com/lumber-identification/hardwoods/koa/", "thumbnailLink": "https://encrypted-tbn1.gstatic.com/images?q=tbn:ANd9GcSMVdvQ6s43dYPEJRbS75-IyCuu9KGEQ9q02vvowWXZn_5GiquaJdrWJb8n5w", "thumbnailHeight": 135}}, {"kind": "customsearch#result", "title": "Sitka Spruce | The Wood Database - Lumber Identification (Softwoods)", "displayLink": "www.wood-database.com", "htmlTitle": "Sitka Spruce | The Wood Database - Lumber Identification (Softwoods)", "snippet": "sitka-spruce.jpg", "htmlSnippet": "sitka-spruce.jpg", "link": "http://www.wood-database.com/wp-content/uploads/sitka-spruce.jpg", "mime": "image/jpeg", "image": {"thumbnailWidth": 135, "byteSize": 72416, "height": 600, "width": 600, "contextLink": "http://www.wood-database.com/lumber-identification/softwoods/sitka-spruce/", "thumbnailLink": "https://encrypted-tbn1.gstatic.com/images?q=tbn:ANd9GcRmONFpFa7Bb3i4e6CgA1dEZyrFCLkrY86CdDM6An6pWCanaZAnhLCd7YwJ", "thumbnailHeight": 135}}, {"kind": "customsearch#result", "title": "Teak | The Wood Database - Lumber Identification (Hardwoods)", "displayLink": "www.wood-database.com", "htmlTitle": "Teak | The Wood Database - Lumber Identification (Hardwoods)", "snippet": "Teak (curly)", "htmlSnippet": "Teak (curly)", "link": "http://www.wood-database.com/wp-content/uploads/teak-curly-s.jpg", "mime": "image/jpeg", "image": {"thumbnailWidth": 135, "byteSize": 155335, "height": 600, "width": 600, "contextLink": "http://www.wood-database.com/lumber-identification/hardwoods/teak/", "thumbnailLink": "https://encrypted-tbn3.gstatic.com/images?q=tbn:ANd9GcRZO7QQtGrgDhoVHNXiYRWbp_psIVHy0e2ro3Zthoi2mDdRixQY2dmligN4pg", "thumbnailHeight": 135}}, {"kind": "customsearch#result", "title": "Pau Ferro | The Wood Database - Lumber Identification (Hardwoods)", "displayLink": "www.wood-database.com", "htmlTitle": "Pau Ferro | The Wood Database - Lumber Identification (Hardwoods)", "snippet": "Pau Ferro (sealed)", "htmlSnippet": "Pau Ferro (sealed)", "link": "http://www.wood-database.com/wp-content/uploads/pau-ferro-sealed.jpg", "mime": "image/jpeg", "image": {"thumbnailWidth": 135, "byteSize": 98842, "height": 600, "width": 600, "contextLink": "http://www.wood-database.com/lumber-identification/hardwoods/pau-ferro/", "thumbnailLink": "https://encrypted-tbn3.gstatic.com/images?q=tbn:ANd9GcSL4ht3__H2gZ82vj0lZS7R9x-PjACvFde3AahXD3aqn9VcB0W0ktOc18Ao", "thumbnailHeight": 135}}, {"kind": "customsearch#result", "title": "Basswood | The Wood Database - Lumber Identification (Hardwoods)", "displayLink": "www.wood-database.com", "htmlTitle": "Basswood | The Wood Database - Lumber Identification (Hardwoods)", "snippet": "Basswood (sealed)", "htmlSnippet": "Basswood (sealed)", "link": "http://www.wood-database.com/wp-content/uploads/basswood-sealed.jpg", "mime": "image/jpeg", "image": {"thumbnailWidth": 135, "byteSize": 116942, "height": 600, "width": 600, "contextLink": "http://www.wood-database.com/lumber-identification/hardwoods/basswood/", "thumbnailLink": "https://encrypted-tbn0.gstatic.com/images?q=tbn:ANd9GcQuAUl-RNLUJwTzI-4FfcbkfNmTSPcAJSCTQ9HaqorSCVaHACBFjWM3oWdb0A", "thumbnailHeight": 135}}, {"kind": "customsearch#result", "title": "Swamp White Oak | The Wood Database - Lumber Identification ...", "displayLink": "www.wood-database.com", "htmlTitle": "Swamp White Oak | The Wood Database - Lumber Identification <b>...</b>", "snippet": "Swamp White Oak (sealed)", "htmlSnippet": "Swamp White Oak (sealed)", "link": "http://www.wood-database.com/wp-content/uploads/swamp-white-oak-sealed.jpg", "mime": "image/jpeg", "image": {"thumbnailWidth": 101, "byteSize": 156567, "height": 600, "width": 450, "contextLink": "http://www.wood-database.com/lumber-identification/hardwoods/swamp-white-oak/", "thumbnailLink": "https://encrypted-tbn3.gstatic.com/images?q=tbn:ANd9GcS2bOmGAB92IV82uYRfDmLrpyqaqXZYRZoQA2KcXKg6YbuzgXXTX00QHN0u", "thumbnailHeight": 135}}, {"kind": "customsearch#result", "title": "Western Red Cedar | The Wood Database - Lumber Identification ...", "displayLink": "www.wood-database.com", "htmlTitle": "Western Red Cedar | The Wood Database - Lumber Identification <b>...</b>", "snippet": "Western Red Cedar", "htmlSnippet": "Western Red Cedar", "link": "http://www.wood-database.com/wp-content/uploads/western-red-cedar.jpg", "mime": "image/jpeg", "image": {"thumbnailWidth": 135, "byteSize": 87783, "height": 600, "width": 600, "contextLink": "http://www.wood-database.com/lumber-identification/softwoods/western-red-cedar/", "thumbnailLink": "https://encrypted-tbn1.gstatic.com/images?q=tbn:ANd9GcRbZ-E1ksZeMxYyv6kI4-XgSpqUmQXHYOD53562_KkowC8h8XNWqUAqcWAusQ", "thumbnailHeight": 135}}, {"kind": "customsearch#result", "title": "Yellow Birch | The Wood Database - Lumber Identification (Hardwoods)", "displayLink": "www.wood-database.com", "htmlTitle": "Yellow Birch | The Wood Database - Lumber Identification (Hardwoods)", "snippet": "Yellow Birch (Betula", "htmlSnippet": "Yellow Birch (Betula", "link": "http://www.wood-database.com/wp-content/uploads/yellow-birch.jpg", "mime": "image/jpeg", "image": {"thumbnailWidth": 135, "byteSize": 93003, "height": 600, "width": 600, "contextLink": "http://www.wood-database.com/lumber-identification/hardwoods/yellow-birch/", "thumbnailLink": "https://encrypted-tbn1.gstatic.com/images?q=tbn:ANd9GcTJiH73UlYqdnIu9lkM-konNiq5RRYrvPmyDuvFvRxE6tHtFJRZ8kktEh4_1A", "thumbnailHeight": 135}}, {"kind": "customsearch#result", "title": "Teak | The Wood Database - Lumber Identification (Hardwoods)", "displayLink": "www.wood-database.com", "htmlTitle": "Teak | The Wood Database - Lumber Identification (Hardwoods)", "snippet": "Teak (Tectona grandis)", "htmlSnippet": "Teak (Tectona grandis)", "link": "http://www.wood-database.com/wp-content/uploads/teak1.jpg", "mime": "image/jpeg", "image": {"thumbnailWidth": 135, "byteSize": 149630, "height": 600, "width": 600, "contextLink": "http://www.wood-database.com/lumber-identification/hardwoods/teak/", "thumbnailLink": "https://encrypted-tbn0.gstatic.com/images?q=tbn:ANd9GcQWHxyqNKMfWT7qVmL1AokRSRIKZGztT2gZ-B6JNkDbK8fmE4b5RbI_MU0j", "thumbnailHeight": 135}}, {"kind": "customsearch#result", "title": "Peruvian Walnut | The Wood Database - Lumber Identification ...", "displayLink": "www.wood-database.com", "htmlTitle": "Peruvian Walnut | The Wood Database - Lumber Identification <b>...</b>", "snippet": "Peruvian Walnut (Juglans spp.)", "htmlSnippet": "Peruvian Walnut (Juglans spp.)", "link": "http://www.wood-database.com/wp-content/uploads/peruvian-walnut.jpg", "mime": "image/jpeg", "image": {"thumbnailWidth": 135, "byteSize": 95862, "height": 600, "width": 600, "contextLink": "http://www.wood-database.com/lumber-identification/hardwoods/peruvian-walnut/", "thumbnailLink": "https://encrypted-tbn0.gstatic.com/images?q=tbn:ANd9GcSEta-mpM03z-v4WrFnC8J8NPLV3uDvVu9t7UPP-HygSUTd256VTlgbklgshw", "thumbnailHeight": 135}}, {"kind": "customsearch#result", "title": "Black Spruce | The Wood Database - Lumber Identification (Softwoods)", "displayLink": "www.wood-database.com", "htmlTitle": "Black Spruce | The Wood Database - Lumber Identification (Softwoods)", "snippet": "Black Spruce (Picea mariana)", "htmlSnippet": "Black Spruce (Picea mariana)", "link": "http://www.wood-database.com/wp-content/uploads/black-spruce.jpg", "mime": "image/jpeg", "image": {"thumbnailWidth": 98, "byteSize": 133120, "height": 600, "width": 435, "contextLink": "http://www.wood-database.com/lumber-identification/softwoods/black-spruce/", "thumbnailLink": "https://encrypted-tbn2.gstatic.com/images?q=tbn:ANd9GcTkg_25jzjfvOCvmfWDRDWoQ_frlgUEWdwXiVTyq5t1vGzDyPBUsDgkom5B", "thumbnailHeight": 135}}, {"kind": "customsearch#result", "title": "Tzalam | The Wood Database - Lumber Identification (Hardwoods)", "displayLink": "www.wood-database.com", "htmlTitle": "Tzalam | The Wood Database - Lumber Identification (Hardwoods)", "snippet": "Tzalam (sealed)", "htmlSnippet": "Tzalam (sealed)", "link": "http://www.wood-database.com/wp-content/uploads/tzalam-sealed.jpg", "mime": "image/jpeg", "image": {"thumbnailWidth": 102, "byteSize": 191615, "height": 600, "width": 455, "contextLink": "http://www.wood-database.com/lumber-identification/hardwoods/tzalam/", "thumbnailLink": "https://encrypted-tbn3.gstatic.com/images?q=tbn:ANd9GcS5jevhdAMhj-8cWUbEdPUdAUc1yWzSpJcgkhF2gYScdCxmlsnHuTZYRXhA", "thumbnailHeight": 135}}, {"kind": "customsearch#result", "title": "Scots Pine | The Wood Database - Lumber Identification (Softwoods)", "displayLink": "www.wood-database.com", "htmlTitle": "Scots Pine | The Wood Database - Lumber Identification (Softwoods)", "snippet": "Scots Pine (Pinus sylvestris)", "htmlSnippet": "Scots Pine (Pinus sylvestris)", "link": "http://www.wood-database.com/wp-content/uploads/scots-pine.jpg", "mime": "image/jpeg", "image": {"thumbnailWidth": 102, "byteSize": 136197, "height": 600, "width": 455, "contextLink": "http://www.wood-database.com/lumber-identification/softwoods/scots-pine/", "thumbnailLink": "https://encrypted-tbn1.gstatic.com/images?q=tbn:ANd9GcRQcURIRu3cJDHfSGN0W5Ej4e38nTX_YnbTF8FtJQ0XJLkK0G5x9t6-cFKb", "thumbnailHeight": 135}}, {"kind": "customsearch#result", "title": "Sitka Spruce | The Wood Database - Lumber Identification (Softwoods)", "displayLink": "www.wood-database.com", "htmlTitle": "Sitka Spruce | The Wood Database - Lumber Identification (Softwoods)", "snippet": "Sitka Spruce (sealed)", "htmlSnippet": "Sitka Spruce (sealed)", "link": "http://www.wood-database.com/wp-content/uploads/sitka-spruce-sealed.jpg", "mime": "image/jpeg", "image": {"thumbnailWidth": 135, "byteSize": 73352, "height": 600, "width": 600, "contextLink": "http://www.wood-database.com/lumber-identification/softwoods/sitka-spruce/", "thumbnailLink": "https://encrypted-tbn2.gstatic.com/images?q=tbn:ANd9GcQiNYSYDvXfYgU0mDSp5vD8fvFDns_Dj9NVO3JgkM8VxcfyBQyG5dhEhJE7", "thumbnailHeight": 135}}, {"kind": "customsearch#result", "title": "Chestnut Oak | The Wood Database - Lumber Identification (Hardwoods)", "displayLink": "www.wood-database.com", "htmlTitle": "Chestnut Oak | The Wood Database - Lumber Identification (Hardwoods)", "snippet": "Chestnut Oak (Quercus prinus)", "htmlSnippet": "Chestnut Oak (Quercus prinus)", "link": "http://www.wood-database.com/wp-content/uploads/chestnut-oak.jpg", "mime": "image/jpeg", "image": {"thumbnailWidth": 100, "byteSize": 163130, "height": 600, "width": 445, "contextLink": "http://www.wood-database.com/lumber-identification/hardwoods/chestnut-oak/", "thumbnailLink": "https://encrypted-tbn3.gstatic.com/images?q=tbn:ANd9GcRcbxxwZoLgiUJin7b3E9MmqjWMxuypPbQLaoylNWYZgRwzujihH4WhX8w", "thumbnailHeight": 135}}, {"kind": "customsearch#result", "title": "Burmese Rosewood | The Wood Database - Lumber Identification ...", "displayLink": "www.wood-database.com", "htmlTitle": "Burmese Rosewood | The Wood Database - Lumber Identification <b>...</b>", "snippet": "Burmese Rosewood (sealed)", "htmlSnippet": "Burmese Rosewood (sealed)", "link": "http://www.wood-database.com/wp-content/uploads/burmese-rosewood-sealed.jpg", "mime": "image/jpeg", "image": {"thumbnailWidth": 95, "byteSize": 148337, "height": 600, "width": 423, "contextLink": "http://www.wood-database.com/lumber-identification/hardwoods/burmese-rosewood/", "thumbnailLink": "https://encrypted-tbn3.gstatic.com/images?q=tbn:ANd9GcSTfzKvwMuoetRpdVK94SCQwuhxI9FGmBcMR1Da1_i1z1riagOccaED7G8", "thumbnailHeight": 135}}, {"kind": "customsearch#result", "title": "Western Larch | The Wood Database - Lumber Identification (Softwoods)", "displayLink": "www.wood-database.com", "htmlTitle": "Western Larch | The Wood Database - Lumber Identification (Softwoods)", "snippet": "Western Larch (Larix", "htmlSnippet": "Western Larch (Larix", "link": "http://www.wood-database.com/wp-content/uploads/western-larch.jpg", "mime": "image/jpeg", "image": {"thumbnailWidth": 98, "byteSize": 165404, "height": 600, "width": 435, "contextLink": "http://www.wood-database.com/lumber-identification/softwoods/western-larch/", "thumbnailLink": "https://encrypted-tbn1.gstatic.com/images?q=tbn:ANd9GcSOKEr-6H7TfHd1dvoWKXhiF_gMrYk363yYLcNnhfRJ6SVAJkFmd6Jzeblt", "thumbnailHeight": 135}}, {"kind": "customsearch#result", "title": "Bleached Burlap | Naturals Burlap | Lamin-Art", "displayLink": "www.laminart.com", "htmlTitle": "Bleached Burlap | Naturals Burlap | Lamin-Art", "snippet": "501 Bleached Burlap - Relief", "htmlSnippet": "501 Bleached Burlap - Relief", "link": "http://www.laminart.com/img/product/cad/893_905_501_L.jpg", "mime": "image/jpeg", "image": {"thumbnailWidth": 150, "byteSize": 2072291, "height": 1400, "width": 1400, "contextLink": "http://www.laminart.com/products-samples/decorative-laminate/naturals-burlap/517/bleached-burlap", "thumbnailLink": "https://encrypted-tbn3.gstatic.com/images?q=tbn:ANd9GcTzzUsQgQqjcdUFNhNVMSHETIfxuH7hygj498mMyxEYRBWYBpiLKhSdClHa", "thumbnailHeight": 150}}, {"kind": "customsearch#result", "title": "Black Walnut | The Wood Database - Lumber Identification (Hardwoods)", "displayLink": "www.wood-database.com", "htmlTitle": "Black Walnut | The Wood Database - Lumber Identification (Hardwoods)", "snippet": "Black Walnut (burl)", "htmlSnippet": "Black Walnut (burl)", "link": "http://www.wood-database.com/wp-content/uploads/black-walnut-burl-s.jpg", "mime": "image/jpeg", "image": {"thumbnailWidth": 135, "byteSize": 111579, "height": 600, "width": 600, "contextLink": "http://www.wood-database.com/lumber-identification/hardwoods/black-walnut/", "thumbnailLink": "https://encrypted-tbn2.gstatic.com/images?q=tbn:ANd9GcSYg8SMgWk0VEzrAWkMTxtsK52eY-mEM1nfwHNa-UJ-Azgs5qCZu3oX-jC9", "thumbnailHeight": 135}}, {"kind": "customsearch#result", "title": "English Elm | The Wood Database - Lumber Identification (Hardwoods)", "displayLink": "www.wood-database.com", "htmlTitle": "English Elm | The Wood Database - Lumber Identification (Hardwoods)", "snippet": "English Elm (veneer)", "htmlSnippet": "English Elm (veneer)", "link": "http://www.wood-database.com/wp-content/uploads/english-elm-veneer-s.jpg", "mime": "image/jpeg", "image": {"thumbnailWidth": 135, "byteSize": 152377, "height": 600, "width": 600, "contextLink": "http://www.wood-database.com/lumber-identification/hardwoods/english-elm/", "thumbnailLink": "https://encrypted-tbn0.gstatic.com/images?q=tbn:ANd9GcSDEH9cPXL9ir273TeKgwgAAxWtLqiyVKebaE1p3AmeRqgScgddcgylQjWaJw", "thumbnailHeight": 135}}, {"kind": "customsearch#result", "title": "Australian Cypress | The Wood Database - Lumber Identification ...", "displayLink": "www.wood-database.com", "htmlTitle": "Australian Cypress | The Wood Database - Lumber Identification <b>...</b>", "snippet": "Australian Cypress (Callitris", "htmlSnippet": "Australian Cypress (Callitris", "link": "http://www.wood-database.com/wp-content/uploads/australian-cypress.jpg", "mime": "image/jpeg", "image": {"thumbnailWidth": 135, "byteSize": 130683, "height": 600, "width": 600, "contextLink": "http://www.wood-database.com/lumber-identification/softwoods/australian-cypress/", "thumbnailLink": "https://encrypted-tbn3.gstatic.com/images?q=tbn:ANd9GcQ1ePpVK4sWAbBrcI6-SaTNUfHq7LA4Zz1D8-sXvTMelXNKLqz4K0NnQhrIIw", "thumbnailHeight": 135}}, {"kind": "customsearch#result", "title": "Plum | The Wood Database - Lumber Identification (Hardwoods)", "displayLink": "www.wood-database.com", "htmlTitle": "Plum | The Wood Database - Lumber Identification (Hardwoods)", "snippet": "Plum (Prunus domestica)", "htmlSnippet": "Plum (Prunus domestica)", "link": "http://www.wood-database.com/wp-content/uploads/plum.jpg", "mime": "image/jpeg", "image": {"thumbnailWidth": 135, "byteSize": 127012, "height": 600, "width": 600, "contextLink": "http://www.wood-database.com/lumber-identification/hardwoods/plum/", "thumbnailLink": "https://encrypted-tbn0.gstatic.com/images?q=tbn:ANd9GcR9QTP8qxSCnNvLuNXxKD8Ugd5wD4WxIQx3dXtKXzjpoLH4KkBlKMnOCM-clg", "thumbnailHeight": 135}}, {"kind": "customsearch#result", "title": "European Lime | The Wood Database - Lumber Identification (Hardwoods)", "displayLink": "www.wood-database.com", "htmlTitle": "European Lime | The Wood Database - Lumber Identification (Hardwoods)", "snippet": "European Lime (Tilia x", "htmlSnippet": "European Lime (Tilia x", "link": "http://www.wood-database.com/wp-content/uploads/european-lime-s.jpg", "mime": "image/jpeg", "image": {"thumbnailWidth": 135, "byteSize": 70666, "height": 600, "width": 600, "contextLink": "http://www.wood-database.com/lumber-identification/hardwoods/european-lime/", "thumbnailLink": "https://encrypted-tbn3.gstatic.com/images?q=tbn:ANd9GcRATgoEvhqPCjkrDdQv62pClpty3LPW2t5X5P7xzN5TOduLQM7WrAUkLBCAAw", "thumbnailHeight": 135}}, {"kind": "customsearch#result", "title": "Regency Cherry | Premium Wood Prints | Lamin-Art", "displayLink": "www.laminart.com", "htmlTitle": "Regency Cherry | Premium Wood Prints | Lamin-Art", "snippet": "3019 Regency Cherry - Textured", "htmlSnippet": "3019 Regency Cherry - <b>Textured</b>", "link": "http://www.laminart.com/img/product/cad/39_3019_cad.jpg", "mime": "image/jpeg", "image": {"thumbnailWidth": 150, "byteSize": 719030, "height": 1400, "width": 1400, "contextLink": "http://www.laminart.com/products-samples/decorative-laminate/premium-wood-prints/62/regency-cherry", "thumbnailLink": "https://encrypted-tbn0.gstatic.com/images?q=tbn:ANd9GcQPjgSE7-JHsOsWMK1pPl_rSBOp-CzMs51Q5GFUtts6V7POeAYasu1neXqNMA", "thumbnailHeight": 150}}, {"kind": "customsearch#result", "title": "Cedar Elm | The Wood Database - Lumber Identification (Hardwoods)", "displayLink": "www.wood-database.com", "htmlTitle": "Cedar Elm | The Wood Database - Lumber Identification (Hardwoods)", "snippet": "Cedar Elm (Ulmus crassifolia)", "htmlSnippet": "Cedar Elm (Ulmus crassifolia)", "link": "http://www.wood-database.com/wp-content/uploads/cedar-elm.jpg", "mime": "image/jpeg", "image": {"thumbnailWidth": 99, "byteSize": 119024, "height": 600, "width": 440, "contextLink": "http://www.wood-database.com/lumber-identification/hardwoods/cedar-elm/", "thumbnailLink": "https://encrypted-tbn1.gstatic.com/images?q=tbn:ANd9GcTwQitbV-YSddDv6HybHeLMi4sjogLQDSMkk61TDlhFdQLux8oW83nSuFnA", "thumbnailHeight": 135}}, {"kind": "customsearch#result", "title": "Red Maple | The Wood Database - Lumber Identification (Hardwoods)", "displayLink": "www.wood-database.com", "htmlTitle": "Red Maple | The Wood Database - Lumber Identification (Hardwoods)", "snippet": "Red Maple (sealed)", "htmlSnippet": "Red Maple (sealed)", "link": "http://www.wood-database.com/wp-content/uploads/red-maple-sealed-2.jpg", "mime": "image/jpeg", "image": {"thumbnailWidth": 99, "byteSize": 163182, "height": 600, "width": 440, "contextLink": "http://www.wood-database.com/lumber-identification/hardwoods/red-maple/", "thumbnailLink": "https://encrypted-tbn3.gstatic.com/images?q=tbn:ANd9GcSdroQYKmSc_R0E_ZHCP4fk8eSbSTPnjfUn6M1J2nRcIG13EHZB-wXG9J_I", "thumbnailHeight": 135}}, {"kind": "customsearch#result", "title": "Peruvian Walnut | The Wood Database - Lumber Identification ...", "displayLink": "www.wood-database.com", "htmlTitle": "Peruvian Walnut | The Wood Database - Lumber Identification <b>...</b>", "snippet": "Peruvian Walnut (sealed)", "htmlSnippet": "Peruvian Walnut (sealed)", "link": "http://www.wood-database.com/wp-content/uploads/peruvian-walnut-sealed1.jpg", "mime": "image/jpeg", "image": {"thumbnailWidth": 135, "byteSize": 113115, "height": 600, "width": 600, "contextLink": "http://www.wood-database.com/lumber-identification/hardwoods/peruvian-walnut/", "thumbnailLink": "https://encrypted-tbn2.gstatic.com/images?q=tbn:ANd9GcRM0Ad8uaEMEuV1FqibGjhXVq6oqxqBhRB5dC6huHYCGx_GjM9toOOArZH-LQ", "thumbnailHeight": 135}}, {"kind": "customsearch#result", "title": "Koto | The Wood Database - Lumber Identification (Hardwoods)", "displayLink": "www.wood-database.com", "htmlTitle": "Koto | The Wood Database - Lumber Identification (Hardwoods)", "snippet": "Koto (gray veneer)", "htmlSnippet": "Koto (gray veneer)", "link": "http://www.wood-database.com/wp-content/uploads/koto-gray.jpg", "mime": "image/jpeg", "image": {"thumbnailWidth": 135, "byteSize": 146207, "height": 600, "width": 600, "contextLink": "http://www.wood-database.com/lumber-identification/hardwoods/koto/", "thumbnailLink": "https://encrypted-tbn1.gstatic.com/images?q=tbn:ANd9GcRG6P7LKud-3gO4-64luCytKp3Rp-ausvZ1zupc7kMlRDubnJn4JhTu8WIuww", "thumbnailHeight": 135}}, {"kind": "customsearch#result", "title": "Smoky Bronze | New products | Lamin-Art", "displayLink": "www.laminart.com", "htmlTitle": "Smoky Bronze | New products | Lamin-Art", "snippet": "4013 Smoky Bronze - Chrysalis", "htmlSnippet": "4013 Smoky Bronze - Chrysalis", "link": "http://www.laminart.com/img/product/cad/345_4013_cad.jpg", "mime": "image/jpeg", "image": {"thumbnailWidth": 150, "byteSize": 1833692, "height": 1400, "width": 1400, "contextLink": "http://www.laminart.com/products-samples/veneer-art/new-products/344/smoky-bronze", "thumbnailLink": "https://encrypted-tbn2.gstatic.com/images?q=tbn:ANd9GcRzD4IhGieBiIKkpRY2xafsPv7KTbJIq_U3wAJXdepAyHe1va9Uluq7jf1q", "thumbnailHeight": 150}}, {"kind": "customsearch#result", "title": "Pau Ferro | The Wood Database - Lumber Identification (Hardwoods)", "displayLink": "www.wood-database.com", "htmlTitle": "Pau Ferro | The Wood Database - Lumber Identification (Hardwoods)", "snippet": "Pau Ferro (endgrain 10x)", "htmlSnippet": "Pau Ferro (endgrain 10x)", "link": "http://www.wood-database.com/wp-content/uploads/pau-ferro-endgrain-zoom.jpg", "mime": "image/jpeg", "image": {"thumbnailWidth": 135, "byteSize": 101673, "height": 600, "width": 600, "contextLink": "http://www.wood-database.com/lumber-identification/hardwoods/pau-ferro/", "thumbnailLink": "https://encrypted-tbn1.gstatic.com/images?q=tbn:ANd9GcT1TY0eWRoMKg9_m5mmFHiu-E2nDZtf5d9f9Gat1irwCBNFNWjMGZ9z02KrVw", "thumbnailHeight": 135}}, {"kind": "customsearch#result", "title": "European Hornbeam | The Wood Database - Lumber Identification ...", "displayLink": "www.wood-database.com", "htmlTitle": "European Hornbeam | The Wood Database - Lumber Identification <b>...</b>", "snippet": "European Hornbeam (Carpinus", "htmlSnippet": "European Hornbeam (Carpinus", "link": "http://www.wood-database.com/wp-content/uploads/european-hornbeam.jpg", "mime": "image/jpeg", "image": {"thumbnailWidth": 99, "byteSize": 111159, "height": 600, "width": 440, "contextLink": "http://www.wood-database.com/lumber-identification/hardwoods/european-hornbeam/", "thumbnailLink": "https://encrypted-tbn3.gstatic.com/images?q=tbn:ANd9GcSMwNHjC0-TWQ8V5BxegJPaU9MRyzhicZ_CnDK1cbEB7rwSMvVF3bbjy8M2", "thumbnailHeight": 135}}, {"kind": "customsearch#result", "title": "Mango | The Wood Database - Lumber Identification (Hardwoods)", "displayLink": "www.wood-database.com", "htmlTitle": "Mango | The Wood Database - Lumber Identification (Hardwoods)", "snippet": "Mango (sealed)", "htmlSnippet": "Mango (sealed)", "link": "http://www.wood-database.com/wp-content/uploads/mango-sealed.jpg", "mime": "image/jpeg", "image": {"thumbnailWidth": 135, "byteSize": 394744, "height": 600, "width": 600, "contextLink": "http://www.wood-database.com/lumber-identification/hardwoods/mango/", "thumbnailLink": "https://encrypted-tbn0.gstatic.com/images?q=tbn:ANd9GcSAgCFZwa7P6mt5wwCVUJiiOQ-RuFh_i06L2iEKFZwXzpBYitS1dVhRWiY6Hw", "thumbnailHeight": 135}}, {"kind": "customsearch#result", "title": "Softwood Anatomy | The Wood Database", "displayLink": "www.wood-database.com", "htmlTitle": "Softwood Anatomy | The Wood Database", "snippet": "Aromatic Red Cedar (endgrain", "htmlSnippet": "Aromatic Red Cedar (endgrain", "link": "http://www.wood-database.com/wp-content/uploads/aromatic-red-cedar-endgrain-zoom.jpg", "mime": "image/jpeg", "image": {"thumbnailWidth": 135, "byteSize": 108665, "height": 600, "width": 600, "contextLink": "http://www.wood-database.com/wood-articles/softwood-anatomy/", "thumbnailLink": "https://encrypted-tbn0.gstatic.com/images?q=tbn:ANd9GcTxi7HddN1yb9-55O7FKxdcXbhMewxmGn_jf_o6GNp9-30kfYfLU0JvijZEDg", "thumbnailHeight": 135}}, {"kind": "customsearch#result", "title": "6 Rustic, Reclaimed, Weathered, Distressed Alder Wood Finishes You ...", "displayLink": "www.woodworkerssource.com", "htmlTitle": "6 Rustic, Reclaimed, Weathered, Distressed Alder Wood Finishes You <b>...</b>", "snippet": "and ridges of the textured", "htmlSnippet": "and ridges of the <b>textured</b>", "link": "http://www.woodworkerssource.com/blog/wp-content/uploads/2014/08/alder-weathered-001.jpg", "mime": "image/jpeg", "image": {"thumbnailWidth": 150, "byteSize": 265150, "height": 683, "width": 1024, "contextLink": "http://www.woodworkerssource.com/blog/tips-tricks/6-alder-wood-finishes-for-rustic-reclaimed-weathered-or-distressed-looks/", "thumbnailLink": "https://encrypted-tbn0.gstatic.com/images?q=tbn:ANd9GcQx6pcwjb1nvjbBvbiMkUDJPXAT-Ho6SmG1tFUT-Hu9yNFbYV1_7S1O6vaZ", "thumbnailHeight": 100}}, {"kind": "customsearch#result", "title": "Balau | The Wood Database - Lumber Identification (Hardwoods)", "displayLink": "www.wood-database.com", "htmlTitle": "Balau | The Wood Database - Lumber Identification (Hardwoods)", "snippet": "Light Red Meranti (Shorea spp.", "htmlSnippet": "Light Red Meranti (Shorea spp.", "link": "http://www.wood-database.com/wp-content/uploads/light-red-meranti-copy.jpg", "mime": "image/jpeg", "image": {"thumbnailWidth": 100, "byteSize": 177561, "height": 600, "width": 445, "contextLink": "http://www.wood-database.com/lumber-identification/hardwoods/balau/", "thumbnailLink": "https://encrypted-tbn3.gstatic.com/images?q=tbn:ANd9GcTdi3ko7nccFrsJh4dEAz-H0WI76lDNRdj5OjZjsYuOUJlDnP81z1or_56_", "thumbnailHeight": 135}}, {"kind": "customsearch#result", "title": "Narra | The Wood Database - Lumber Identification (Hardwoods)", "displayLink": "www.wood-database.com", "htmlTitle": "Narra | The Wood Database - Lumber Identification (Hardwoods)", "snippet": "Narra (Pterocarpus indicus)", "htmlSnippet": "Narra (Pterocarpus indicus)", "link": "http://www.wood-database.com/wp-content/uploads/narra-3.jpg", "mime": "image/jpeg", "image": {"thumbnailWidth": 135, "byteSize": 139127, "height": 600, "width": 600, "contextLink": "http://www.wood-database.com/lumber-identification/hardwoods/narra/", "thumbnailLink": "https://encrypted-tbn2.gstatic.com/images?q=tbn:ANd9GcQ2bzy9Mnb-RUX81HkrFSGMMj3I4rDgoeRtEwsftzQGjUCTF8avs2aY0O4Y", "thumbnailHeight": 135}}, {"kind": "customsearch#result", "title": "Pau Ferro | The Wood Database - Lumber Identification (Hardwoods)", "displayLink": "www.wood-database.com", "htmlTitle": "Pau Ferro | The Wood Database - Lumber Identification (Hardwoods)", "snippet": "Pau Ferro (Machaerium spp.)", "htmlSnippet": "Pau Ferro (Machaerium spp.)", "link": "http://www.wood-database.com/wp-content/uploads/pau-ferro.jpg", "mime": "image/jpeg", "image": {"thumbnailWidth": 135, "byteSize": 99432, "height": 600, "width": 600, "contextLink": "http://www.wood-database.com/lumber-identification/hardwoods/pau-ferro/", "thumbnailLink": "https://encrypted-tbn3.gstatic.com/images?q=tbn:ANd9GcTx6DpGxay760_J5qBq_ehG7sstP8fPz3d3tsCRYTFzchRDcFi737d8By6M", "thumbnailHeight": 135}}, {"kind": "customsearch#result", "title": "Nyatoh | The Wood Database - Lumber Identification (Hardwoods)", "displayLink": "www.wood-database.com", "htmlTitle": "Nyatoh | The Wood Database - Lumber Identification (Hardwoods)", "snippet": "Nyatoh (Palaquium spp.)", "htmlSnippet": "Nyatoh (Palaquium spp.)", "link": "http://www.wood-database.com/wp-content/uploads/nyatoh.jpg", "mime": "image/jpeg", "image": {"thumbnailWidth": 93, "byteSize": 172079, "height": 600, "width": 415, "contextLink": "http://www.wood-database.com/lumber-identification/hardwoods/nyatoh/", "thumbnailLink": "https://encrypted-tbn0.gstatic.com/images?q=tbn:ANd9GcSTMyGNU-uSvRjqbcfRndMdXBnHx33TgHs-fx4ir6tdQ64xpMAMsFz_zXM", "thumbnailHeight": 135}}, {"kind": "customsearch#result", "title": "Rubberwood | The Wood Database - Lumber Identification (Hardwoods)", "displayLink": "www.wood-database.com", "htmlTitle": "Rubberwood | The Wood Database - Lumber Identification (Hardwoods)", "snippet": "rubberwood.jpg", "htmlSnippet": "rubberwood.jpg", "link": "http://www.wood-database.com/wp-content/uploads/rubberwood.jpg", "mime": "image/jpeg", "image": {"thumbnailWidth": 93, "byteSize": 120968, "height": 600, "width": 415, "contextLink": "http://www.wood-database.com/lumber-identification/hardwoods/rubberwood/", "thumbnailLink": "https://encrypted-tbn1.gstatic.com/images?q=tbn:ANd9GcR0cNqdWUA_B8fYhqP06bdaceGyR8dd-jLT8HyeYpdr4tNvYXt_AB0R1EU", "thumbnailHeight": 135}}, {"kind": "customsearch#result", "title": "Norway Spruce | The Wood Database - Lumber Identification (Softwoods)", "displayLink": "www.wood-database.com", "htmlTitle": "Norway Spruce | The Wood Database - Lumber Identification (Softwoods)", "snippet": "Norway Spruce (Picea abies)", "htmlSnippet": "Norway Spruce (Picea abies)", "link": "http://www.wood-database.com/wp-content/uploads/norway-spruce.jpg", "mime": "image/jpeg", "image": {"thumbnailWidth": 98, "byteSize": 147068, "height": 600, "width": 435, "contextLink": "http://www.wood-database.com/lumber-identification/softwoods/norway-spruce/", "thumbnailLink": "https://encrypted-tbn0.gstatic.com/images?q=tbn:ANd9GcRWVIjBDRC8Dunt1ekZ09Nado2HhDYq-e0MAB5HGEulqsje5Wbmtf_o8Ao", "thumbnailHeight": 135}}, {"kind": "customsearch#result", "title": "Brazilian Rosewood | The Wood Database - Lumber Identification ...", "displayLink": "www.wood-database.com", "htmlTitle": "Brazilian Rosewood | The Wood Database - Lumber Identification <b>...</b>", "snippet": "Brazilian Rosewood (sealed)", "htmlSnippet": "Brazilian Rosewood (sealed)", "link": "http://www.wood-database.com/wp-content/uploads/brazilian-rosewood-sealed.jpg", "mime": "image/jpeg", "image": {"thumbnailWidth": 88, "byteSize": 68285, "height": 600, "width": 393, "contextLink": "http://www.wood-database.com/lumber-identification/hardwoods/brazilian-rosewood/", "thumbnailLink": "https://encrypted-tbn0.gstatic.com/images?q=tbn:ANd9GcSzv92CU8owHqn-3vPuN8iytiX0FDZa35qTlaYHeU_h5A9HosH45anH5_0", "thumbnailHeight": 135}}, {"kind": "customsearch#result", "title": "Sissoo | The Wood Database - Lumber Identification (Hardwoods)", "displayLink": "www.wood-database.com", "htmlTitle": "Sissoo | The Wood Database - Lumber Identification (Hardwoods)", "snippet": "Sissoo (Dalbergia sissoo)", "htmlSnippet": "Sissoo (Dalbergia sissoo)", "link": "http://www.wood-database.com/wp-content/uploads/sissoo-2.jpg", "mime": "image/jpeg", "image": {"thumbnailWidth": 99, "byteSize": 159445, "height": 600, "width": 440, "contextLink": "http://www.wood-database.com/lumber-identification/hardwoods/sissoo/", "thumbnailLink": "https://encrypted-tbn0.gstatic.com/images?q=tbn:ANd9GcTMiz7BScMJzCYkp7thYV8wuLph52txqGMFX5WqSF8PK5DxNm8xyGqO-b6G", "thumbnailHeight": 135}}, {"kind": "customsearch#result", "title": "Cypress | The Wood Database - Lumber Identification (Softwoods)", "displayLink": "www.wood-database.com", "htmlTitle": "Cypress | The Wood Database - Lumber Identification (Softwoods)", "snippet": "Cypress (Taxodium distichum)", "htmlSnippet": "Cypress (Taxodium distichum)", "link": "http://www.wood-database.com/wp-content/uploads/cypress.jpg", "mime": "image/jpeg", "image": {"thumbnailWidth": 135, "byteSize": 135005, "height": 600, "width": 600, "contextLink": "http://www.wood-database.com/lumber-identification/softwoods/cypress/", "thumbnailLink": "https://encrypted-tbn0.gstatic.com/images?q=tbn:ANd9GcRtLeLnbN_8C8kouOyKLBWSESpg82RTEXsztNN2Dvb0qHZeBVmHKZtU7ZqV7g", "thumbnailHeight": 135}}, {"kind": "customsearch#result", "title": "Merbau | The Wood Database - Lumber Identification (Hardwoods)", "displayLink": "www.wood-database.com", "htmlTitle": "Merbau | The Wood Database - Lumber Identification (Hardwoods)", "snippet": "Merbau (sealed)", "htmlSnippet": "Merbau (sealed)", "link": "http://www.wood-database.com/wp-content/uploads/merbau-sealed.jpg", "mime": "image/jpeg", "image": {"thumbnailWidth": 135, "byteSize": 130963, "height": 600, "width": 600, "contextLink": "http://www.wood-database.com/lumber-identification/hardwoods/merbau/", "thumbnailLink": "https://encrypted-tbn3.gstatic.com/images?q=tbn:ANd9GcT-qCXmsBeBFsKs-wVKe-WxBo_0k9wt2Zs9OCr-P2EIWct-D6luvoxOiZLFMw", "thumbnailHeight": 135}}, {"kind": "customsearch#result", "title": "Redwood | The Wood Database - Lumber Identification (Softwoods)", "displayLink": "www.wood-database.com", "htmlTitle": "Redwood | The Wood Database - Lumber Identification (Softwoods)", "snippet": "Redwood (sealed)", "htmlSnippet": "Redwood (sealed)", "link": "http://www.wood-database.com/wp-content/uploads/redwood-sealed.jpg", "mime": "image/jpeg", "image": {"thumbnailWidth": 135, "byteSize": 103294, "height": 600, "width": 600, "contextLink": "http://www.wood-database.com/lumber-identification/softwoods/redwood/", "thumbnailLink": "https://encrypted-tbn2.gstatic.com/images?q=tbn:ANd9GcSGlu-8qNiVkeVXL_z7NNKY7lR7NZgc5-id050P-BzIKDvCWc6urzxnqN88rg", "thumbnailHeight": 135}}, {"kind": "customsearch#result", "title": "Birch White Veneer 2 x 8 Sheet: Paper back veneer - Woodworkers Source", "displayLink": "www.woodworkerssource.com", "htmlTitle": "Birch White Veneer 2 x 8 Sheet: Paper back veneer - Woodworkers Source", "snippet": "Birch White Veneer 2 x 8", "htmlSnippet": "Birch White Veneer 2 x 8", "link": "http://www.woodworkerssource.com/mm5/graphics/woods_stacks_scans/birch_white.jpg", "mime": "image/jpeg", "image": {"thumbnailWidth": 77, "byteSize": 16198, "height": 300, "width": 200, "contextLink": "http://www.woodworkerssource.com/shop/product/20251002.html", "thumbnailLink": "https://encrypted-tbn3.gstatic.com/images?q=tbn:ANd9GcS-wgB6F-itVPIZxT0fRd5EL2HgSazlGKeQ0U-9mTJprJsmh1aRYY2gE6Q", "thumbnailHeight": 116}}, {"kind": "customsearch#result", "title": "Red Maple | The Wood Database - Lumber Identification (Hardwoods)", "displayLink": "www.wood-database.com", "htmlTitle": "Red Maple | The Wood Database - Lumber Identification (Hardwoods)", "snippet": "Red Maple (endgrain 10x)", "htmlSnippet": "Red Maple (endgrain 10x)", "link": "http://www.wood-database.com/wp-content/uploads/red-maple-endgrain-zoom.jpg", "mime": "image/jpeg", "image": {"thumbnailWidth": 135, "byteSize": 299448, "height": 600, "width": 600, "contextLink": "http://www.wood-database.com/lumber-identification/hardwoods/red-maple/", "thumbnailLink": "https://encrypted-tbn0.gstatic.com/images?q=tbn:ANd9GcTeBBxF1lPoNkS5ABVJF8lpr9LStGLuwU2R0e4JskFOXx7hFw7pCLh76V-_EA", "thumbnailHeight": 135}}, {"kind": "customsearch#result", "title": "Sorting Out Satinwoods | The Wood Database", "displayLink": "www.wood-database.com", "htmlTitle": "Sorting Out Satinwoods | The Wood Database", "snippet": "Movingui (coarse texture)", "htmlSnippet": "Movingui (coarse <b>texture</b>)", "link": "http://www.wood-database.com/wp-content/uploads/movingui-texture.jpg", "mime": "image/jpeg", "image": {"thumbnailWidth": 104, "byteSize": 18209, "height": 200, "width": 200, "contextLink": "http://www.wood-database.com/wood-articles/sorting-out-satinwoods/", "thumbnailLink": "https://encrypted-tbn3.gstatic.com/images?q=tbn:ANd9GcTR20SrwBmlGuPp-2UHn8QVi7jo-3IT3Qzunr8gPVYXAgL83yA2zuZMF1I", "thumbnailHeight": 104}}, {"kind": "customsearch#result", "title": "Jarrah | The Wood Database - Lumber Identification (Hardwoods)", "displayLink": "www.wood-database.com", "htmlTitle": "Jarrah | The Wood Database - Lumber Identification (Hardwoods)", "snippet": "Jarrah (sealed)", "htmlSnippet": "Jarrah (sealed)", "link": "http://www.wood-database.com/wp-content/uploads/jarrah-sealed-s.jpg", "mime": "image/jpeg", "image": {"thumbnailWidth": 135, "byteSize": 120294, "height": 600, "width": 600, "contextLink": "http://www.wood-database.com/lumber-identification/hardwoods/jarrah/", "thumbnailLink": "https://encrypted-tbn2.gstatic.com/images?q=tbn:ANd9GcQchhpBhZSpG_1E0Dn7odIGxGacO5HXCnoWys0zOKN1LIYCVuQlQQIOCAQD", "thumbnailHeight": 135}}, {"kind": "customsearch#result", "title": "European Larch | The Wood Database - Lumber Identification (Softwoods)", "displayLink": "www.wood-database.com", "htmlTitle": "European Larch | The Wood Database - Lumber Identification (Softwoods)", "snippet": "Larch (fumed)", "htmlSnippet": "Larch (fumed)", "link": "http://www.wood-database.com/wp-content/uploads/larch-fumed.jpg", "mime": "image/jpeg", "image": {"thumbnailWidth": 135, "byteSize": 152816, "height": 600, "width": 600, "contextLink": "http://www.wood-database.com/lumber-identification/softwoods/european-larch/", "thumbnailLink": "https://encrypted-tbn1.gstatic.com/images?q=tbn:ANd9GcQc183bGBX1XEnGa59aeeGhFI44yMaQAFOqdVIrDZI6Qn0w1aQkJY1sUqUDWg", "thumbnailHeight": 135}}, {"kind": "customsearch#result", "title": "Honduran Rosewood | The Wood Database - Lumber Identification ...", "displayLink": "www.wood-database.com", "htmlTitle": "Honduran Rosewood | The Wood Database - Lumber Identification <b>...</b>", "snippet": "Honduran Rosewood (sealed)", "htmlSnippet": "Honduran Rosewood (sealed)", "link": "http://www.wood-database.com/wp-content/uploads/honduran-rosewood-sealed.jpg", "mime": "image/jpeg", "image": {"thumbnailWidth": 135, "byteSize": 106029, "height": 600, "width": 600, "contextLink": "http://www.wood-database.com/lumber-identification/hardwoods/honduran-rosewood/", "thumbnailLink": "https://encrypted-tbn0.gstatic.com/images?q=tbn:ANd9GcTmWV3NHEhsMTYSwmiZ8XdO__0sZsY0pfGXH-9NVHVCz2L_0VmfB71wUxky", "thumbnailHeight": 135}}, {"kind": "customsearch#result", "title": "Incense Cedar | The Wood Database - Lumber Identification (Softwoods)", "displayLink": "www.wood-database.com", "htmlTitle": "Incense Cedar | The Wood Database - Lumber Identification (Softwoods)", "snippet": "Incense Cedar (Caldocedrus", "htmlSnippet": "Incense Cedar (Caldocedrus", "link": "http://www.wood-database.com/wp-content/uploads/incense-cedar.jpg", "mime": "image/jpeg", "image": {"thumbnailWidth": 99, "byteSize": 156995, "height": 600, "width": 440, "contextLink": "http://www.wood-database.com/lumber-identification/softwoods/incense-cedar/", "thumbnailLink": "https://encrypted-tbn0.gstatic.com/images?q=tbn:ANd9GcTxWUpdksvIyMbEVdDH3mUroMWq38jSRtMheJp6oNLOJzgFnAZ9fYgCJ4o", "thumbnailHeight": 135}}, {"kind": "customsearch#result", "title": "Oregon White Oak | The Wood Database - Lumber Identification ...", "displayLink": "www.wood-database.com", "htmlTitle": "Oregon White Oak | The Wood Database - Lumber Identification <b>...</b>", "snippet": "Oregon White Oak (Quercus", "htmlSnippet": "Oregon White Oak (Quercus", "link": "http://www.wood-database.com/wp-content/uploads/oregon-white-oak.jpg", "mime": "image/jpeg", "image": {"thumbnailWidth": 99, "byteSize": 160808, "height": 600, "width": 440, "contextLink": "http://www.wood-database.com/lumber-identification/hardwoods/oregon-white-oak/", "thumbnailLink": "https://encrypted-tbn3.gstatic.com/images?q=tbn:ANd9GcRqB0OjRq9_-B8AmRwB11lSCnNQbiunbjuWQ0p7ergjhQWGLOC9aHP8up_z", "thumbnailHeight": 135}}, {"kind": "customsearch#result", "title": "Tzalam | The Wood Database - Lumber Identification (Hardwoods)", "displayLink": "www.wood-database.com", "htmlTitle": "Tzalam | The Wood Database - Lumber Identification (Hardwoods)", "snippet": "Tzalam (Lysiloma latisiliquum)", "htmlSnippet": "Tzalam (Lysiloma latisiliquum)", "link": "http://www.wood-database.com/wp-content/uploads/tzalam.jpg", "mime": "image/jpeg", "image": {"thumbnailWidth": 102, "byteSize": 172919, "height": 600, "width": 455, "contextLink": "http://www.wood-database.com/lumber-identification/hardwoods/tzalam/", "thumbnailLink": "https://encrypted-tbn2.gstatic.com/images?q=tbn:ANd9GcTMGkOB89PdtpyZ5XT_BoFCKgPWMX7Sfo5bDIZqbr7x8k6H9uUW7lK73LQ", "thumbnailHeight": 135}}, {"kind": "customsearch#result", "title": "Honduran Rosewood | The Wood Database - Lumber Identification ...", "displayLink": "www.wood-database.com", "htmlTitle": "Honduran Rosewood | The Wood Database - Lumber Identification <b>...</b>", "snippet": "Honduran Rosewood", "htmlSnippet": "Honduran Rosewood", "link": "http://www.wood-database.com/wp-content/uploads/honduran-rosewood.jpg", "mime": "image/jpeg", "image": {"thumbnailWidth": 135, "byteSize": 104019, "height": 600, "width": 600, "contextLink": "http://www.wood-database.com/lumber-identification/hardwoods/honduran-rosewood/", "thumbnailLink": "https://encrypted-tbn2.gstatic.com/images?q=tbn:ANd9GcRjLi7e4UIjjOn_A3iernSp0MMH1nkILfRB5ts9xUGH7ls8AjEtDYja6DJF", "thumbnailHeight": 135}}, {"kind": "customsearch#result", "title": "Bronze Ribbon Mahogany | Premium Wood Prints | Lamin-Art", "displayLink": "www.laminart.com", "htmlTitle": "Bronze Ribbon Mahogany | Premium Wood Prints | Lamin-Art", "snippet": "2613 Bronze Ribbon Mahogany", "htmlSnippet": "2613 Bronze Ribbon Mahogany", "link": "http://www.laminart.com/img/product/cad/27_2613_cad.jpg", "mime": "image/jpeg", "image": {"thumbnailWidth": 150, "byteSize": 799765, "height": 1400, "width": 1400, "contextLink": "http://www.laminart.com/products-samples/decorative-laminate/premium-wood-prints/55/bronze-ribbon-mahogany", "thumbnailLink": "https://encrypted-tbn3.gstatic.com/images?q=tbn:ANd9GcRmT7abciqlbue0Ar8QHae4V1OUne7lF2tvtBhqe_y3Le91EkXJ-6_RWtTm", "thumbnailHeight": 150}}, {"kind": "customsearch#result", "title": "Black Ash | The Wood Database - Lumber Identification (Hardwoods)", "displayLink": "www.wood-database.com", "htmlTitle": "Black Ash | The Wood Database - Lumber Identification (Hardwoods)", "snippet": "Black Ash (sealed)", "htmlSnippet": "Black Ash (sealed)", "link": "http://www.wood-database.com/wp-content/uploads/black-ash-sealed.jpg", "mime": "image/jpeg", "image": {"thumbnailWidth": 101, "byteSize": 173275, "height": 600, "width": 448, "contextLink": "http://www.wood-database.com/lumber-identification/hardwoods/black-ash/", "thumbnailLink": "https://encrypted-tbn2.gstatic.com/images?q=tbn:ANd9GcQfMB8d_ArcSmpGUJfKi7CgtoQGRvcICYA72fglRI6F6KyLH-ZMdzA38Iva", "thumbnailHeight": 135}}, {"kind": "customsearch#result", "title": "White Oak | The Wood Database - Lumber Identification (Hardwoods)", "displayLink": "www.wood-database.com", "htmlTitle": "White Oak | The Wood Database - Lumber Identification (Hardwoods)", "snippet": "White Oak", "htmlSnippet": "White Oak", "link": "http://www.wood-database.com/wp-content/uploads/white-oak.jpg", "mime": "image/jpeg", "image": {"thumbnailWidth": 135, "byteSize": 85834, "height": 600, "width": 600, "contextLink": "http://www.wood-database.com/lumber-identification/hardwoods/white-oak/", "thumbnailLink": "https://encrypted-tbn2.gstatic.com/images?q=tbn:ANd9GcSuhnr_6Vfb9jjpcOkFSEVjcZwbhKfldomrR3bxhrdugvCNpKnVd-66YODGgQ", "thumbnailHeight": 135}}, {"kind": "customsearch#result", "title": "Pitch Pine | The Wood Database - Lumber Identification (Softwoods)", "displayLink": "www.wood-database.com", "htmlTitle": "Pitch Pine | The Wood Database - Lumber Identification (Softwoods)", "snippet": "Pitch Pine (Pinus rigida)", "htmlSnippet": "Pitch Pine (Pinus rigida)", "link": "http://www.wood-database.com/wp-content/uploads/pitch-pine.jpg", "mime": "image/jpeg", "image": {"thumbnailWidth": 100, "byteSize": 114382, "height": 600, "width": 445, "contextLink": "http://www.wood-database.com/lumber-identification/softwoods/pitch-pine/", "thumbnailLink": "https://encrypted-tbn1.gstatic.com/images?q=tbn:ANd9GcTu0nZemfsjCi3oFWchZne9H0SkTBf4fiRORaz6E_h3IB0b5T1bw4jJYAjq", "thumbnailHeight": 135}}, {"kind": "customsearch#result", "title": "Mexican Cypress | The Wood Database - Lumber Identification ...", "displayLink": "www.wood-database.com", "htmlTitle": "Mexican Cypress | The Wood Database - Lumber Identification <b>...</b>", "snippet": "Mexican Cypress (Cupressus", "htmlSnippet": "Mexican Cypress (Cupressus", "link": "http://www.wood-database.com/wp-content/uploads/mexican-cypress.jpg", "mime": "image/jpeg", "image": {"thumbnailWidth": 100, "byteSize": 144628, "height": 600, "width": 445, "contextLink": "http://www.wood-database.com/lumber-identification/softwoods/mexican-cypress/", "thumbnailLink": "https://encrypted-tbn1.gstatic.com/images?q=tbn:ANd9GcRhJhTUltemmUvvZrtpL6zEHuJt8Ab6LgwGuURbO9tA7_IcsvzncgEtbh4", "thumbnailHeight": 135}}, {"kind": "customsearch#result", "title": "African Blackwood | The Wood Database - Lumber Identification ...", "displayLink": "www.wood-database.com", "htmlTitle": "African Blackwood | The Wood Database - Lumber Identification <b>...</b>", "snippet": "African Blackwood (Dalbergia", "htmlSnippet": "African Blackwood (Dalbergia", "link": "http://www.wood-database.com/wp-content/uploads/african-blackwood.jpg", "mime": "image/jpeg", "image": {"thumbnailWidth": 135, "byteSize": 132296, "height": 600, "width": 600, "contextLink": "http://www.wood-database.com/lumber-identification/hardwoods/african-blackwood/", "thumbnailLink": "https://encrypted-tbn2.gstatic.com/images?q=tbn:ANd9GcT845ov0qXpFCSmJUJUXOcjsvxRpZEXrsAbfxDaeI1lHyGGc_falziW3l5L", "thumbnailHeight": 135}}, {"kind": "customsearch#result", "title": "Plum | The Wood Database - Lumber Identification (Hardwoods)", "displayLink": "www.wood-database.com", "htmlTitle": "Plum | The Wood Database - Lumber Identification (Hardwoods)", "snippet": "Plum (endgrain 10x)", "htmlSnippet": "Plum (endgrain 10x)", "link": "http://www.wood-database.com/wp-content/uploads/plum-endgrain-zoom.jpg", "mime": "image/jpeg", "image": {"thumbnailWidth": 135, "byteSize": 144447, "height": 600, "width": 600, "contextLink": "http://www.wood-database.com/lumber-identification/hardwoods/plum/", "thumbnailLink": "https://encrypted-tbn0.gstatic.com/images?q=tbn:ANd9GcS42Fuzjf3LPi3tH5dJ6HIJ8HWO2JhG88TzlqOapMOfcHHUc0BTpev7rvSnCg", "thumbnailHeight": 135}}, {"kind": "customsearch#result", "title": "Striped Maple | The Wood Database - Lumber Identification (Hardwoods)", "displayLink": "www.wood-database.com", "htmlTitle": "Striped Maple | The Wood Database - Lumber Identification (Hardwoods)", "snippet": "Striped Maple (sealed)", "htmlSnippet": "Striped Maple (sealed)", "link": "http://www.wood-database.com/wp-content/uploads/striped-maple-sealed.jpg", "mime": "image/jpeg", "image": {"thumbnailWidth": 99, "byteSize": 152750, "height": 600, "width": 440, "contextLink": "http://www.wood-database.com/lumber-identification/hardwoods/striped-maple/", "thumbnailLink": "https://encrypted-tbn2.gstatic.com/images?q=tbn:ANd9GcROBkHpTHXtZPoh_bC2tuEuvSrroEyVZpv7ojsPmNbx4J4e-CtLulrX4dXn", "thumbnailHeight": 135}}]